engcoolprop/InterpProp_scipy.py
engcoolprop/__init__.py
engcoolprop/_version.py
engcoolprop/banner.py
engcoolprop/conv_funcs.py
engcoolprop/ec_fluid.py
engcoolprop/ec_humid_air.py
engcoolprop/ec_incomp_fluid.py
engcoolprop/ec_incomp_soln.py
engcoolprop/find_exception_threshold.py
engcoolprop/humid_air_params.py
engcoolprop/iteration_utils.py
engcoolprop/parameter_units.py
engcoolprop/root_solver.py
engcoolprop/safe_get_property.py
engcoolprop/si_object.py
engcoolprop/utils.py
engcoolprop/examples/DowQ_enthalpy.png
engcoolprop/examples/MEG_pcent_D.png
engcoolprop/examples/chk_fluid_in_db.py
engcoolprop/examples/chk_incompress.py
engcoolprop/examples/chk_indep_props_incomp.py
engcoolprop/examples/crit_props.py
engcoolprop/examples/dew_point.png
engcoolprop/examples/dir_of_heos_incomp.py
engcoolprop/examples/example_1.py
engcoolprop/examples/example_2.py
engcoolprop/examples/example_h2.py
engcoolprop/examples/example_he.py
engcoolprop/examples/example_inc_soln_meg30.py
engcoolprop/examples/example_inc_soln_meg30_wTP.py
engcoolprop/examples/example_incomp.py
engcoolprop/examples/example_incomp_Acetone.py
engcoolprop/examples/example_incomp_DowQ.py
engcoolprop/examples/example_incomp_water.py
engcoolprop/examples/image_change_on_RST_page.txt
engcoolprop/examples/incomp_propery_options.py
engcoolprop/examples/init_ha_obj.py
engcoolprop/examples/list_all_heos.py
engcoolprop/examples/list_all_incomp.py
engcoolprop/examples/list_humid_air_IO.py
engcoolprop/examples/plot_DowQ_H.py
engcoolprop/examples/plot_MEG_pcents.py
engcoolprop/examples/plot_humidair_H.py
engcoolprop/examples/plot_water_P_w.py
engcoolprop/examples/plot_wetbulb.py
engcoolprop/examples/plot_wetbulb_v2.py
engcoolprop/examples/print_incomp_fluids_solns.py
engcoolprop/examples/run_experiments.py
engcoolprop/examples/sample_plot.py
engcoolprop/examples/water_partial_pressure.png
engcoolprop/tests/__init__.py
engcoolprop/tests/test_ec_fluid.py
engcoolprop/tests/test_humid_air.py
engcoolprop-0.1.11.dist-info/AUTHORS.rst
engcoolprop-0.1.11.dist-info/LICENSE.txt
engcoolprop-0.1.11.dist-info/METADATA
engcoolprop-0.1.11.dist-info/WHEEL
engcoolprop-0.1.11.dist-info/top_level.txt
engcoolprop-0.1.11.dist-info/RECORD
