Metadata-Version: 2.1
Name: engcoolprop
Version: 0.1.11
Summary: EngCoolProp is a python Engineering Units wrapper around the CoolProp project.
Home-page: http://engcoolprop.readthedocs.org/en/latest/
Download-URL: https://github.com/sonofeft/EngCoolProp
Author: Charlie Taylor
Author-email: cet@appliedpython.com
License: GPL-3
Keywords: engcoolprop setuptools development
Platform: any
Classifier: Development Status :: 4 - Beta
Classifier: Operating System :: OS Independent
Classifier: Intended Audience :: Developers
Classifier: Intended Audience :: End Users/Desktop
Classifier: Topic :: Software Development :: Build Tools
Classifier: License :: OSI Approved :: GNU General Public License v3 (GPLv3)
Classifier: Programming Language :: Python :: 3
Classifier: Programming Language :: Python :: 3.7
Classifier: Programming Language :: Python :: 3.8
Classifier: Programming Language :: Python :: 3.9
Classifier: Programming Language :: Python :: 3.10
Classifier: Programming Language :: Python :: 3.11
License-File: LICENSE.txt
License-File: AUTHORS.rst
Requires-Dist: numpy
Requires-Dist: coolprop
Requires-Dist: scipy
Provides-Extra: dev
Requires-Dist: check-manifest ; extra == 'dev'
Provides-Extra: test
Requires-Dist: coverage ; extra == 'test'
